timetree/__init__.py
timetree/frontend.py
timetree/backend/__init__.py
timetree/backend/base.py
timetree/backend/base_dnode.py
timetree/backend/base_linearized_full.py
timetree/backend/base_partial.py
timetree/backend/base_util.py
timetree/backend/bsearch_linearized_full.py
timetree/backend/bsearch_partial.py
timetree/backend/bst_linearized_full.py
timetree/backend/copy.py
timetree/backend/nop.py
timetree/backend/split_linearized_full.py
timetree/backend/split_partial.py
timetree/backend/util/__init__.py
timetree/backend/util/linked_list.py
timetree/backend/util/order_maintenance.py
timetree/backend/util/predecessor.py
timetree-0.1.1.dist-info/DESCRIPTION.rst
timetree-0.1.1.dist-info/METADATA
timetree-0.1.1.dist-info/RECORD
timetree-0.1.1.dist-info/WHEEL
timetree-0.1.1.dist-info/metadata.json
timetree-0.1.1.dist-info/top_level.txt
